 [
        { "url": "https://i.ibb.co/NrNDG7m/photo-18.jpg" },
        { "url": "https://i.ibb.co/vJS0qXp/photo-17.jpg" },
        { "url": "https://i.ibb.co/G0T6mWV/photo-9.jpg" },
        { "url": "https://i.ibb.co/G77FsJN/photo-16.jpg" },
        { "url": "https://i.ibb.co/SspWyTm/photo-15.jpg" },
        { "url": "https://i.ibb.co/CbT0Kds/photo-14.jpg" },
        { "url": "https://i.ibb.co/TgW83zz/photo-13.jpg" },
        { "url": "https://i.ibb.co/cC0wYJm/photo-12.jpg" },
        { "url": "https://i.ibb.co/tb77Lsv/photo-11.jpg" },
        { "url": "https://i.ibb.co/y80vB4z/photo-10.jpg" },
        { "url": "https://i.ibb.co/5Ym1sJr/348.jpg" },
        { "url": "https://i.ibb.co/vHxpNY2/348s.jpg" },
        { "url": "https://i.ibb.co/F6RpmF3/photo-2.jpg" },
        { "url": "https://i.ibb.co/sH2tD1F/photo-4.jpg" },
        { "url": "https://i.ibb.co/NrNDG7m/photo-18.jpg" },
        { "url": "https://i.ibb.co/G77FsJN/photo-16.jpg" },
        { "url": "https://i.ibb.co/G0T6mWV/photo-9.jpg" },
        { "url": "https://i.ibb.co/CbT0Kds/photo-14.jpg" },
        { "url": "https://i.ibb.co/h1bm7KQ/photo-7.jpg" },
        { "url": "https://i.ibb.co/6JtLptw/photo-1.jpg" },
        { "url": "https://i.ibb.co/hFLzVMH/photo-8.jpg" },
        { "url": "https://i.ibb.co/h1bm7KQ/photo-7.jpg" },
        { "url": "https://i.ibb.co/gtkKpbT/photo-6.jpg" },
        { "url": "https://i.ibb.co/6WhWW0m/photo-5.jpg" },
        { "url": "https://i.ibb.co/sH2tD1F/photo-4.jpg" },
        { "url": "https://i.ibb.co/Rvc5VpQ/photo-3.jpg" },
        { "url": "https://i.ibb.co/F6RpmF3/photo-2.jpg" },
        { "url": "https://i.ibb.co/6JtLptw/photo-1.jpg" },
        { "url": "https://i.ibb.co/vHxpNY2/348s.jpg" },
        { "url": "https://i.ibb.co/5Ym1sJr/348.jpg" }
      ]
  
